pyjdbc/__init__.py
pyjdbc/connect.py
pyjdbc/dbapi.py
pyjdbc/exceptions.py
pyjdbc/helpers.py
pyjdbc/java.py
pyjdbc/jdbc.py
pyjdbc/kerberos.py
pyjdbc/sqlite.py
pyjdbc/types.py
pyjdbc-0.2.2.dist-info/LICENSE
pyjdbc-0.2.2.dist-info/METADATA
pyjdbc-0.2.2.dist-info/WHEEL
pyjdbc-0.2.2.dist-info/top_level.txt
pyjdbc-0.2.2.dist-info/RECORD
