Metadata-Version: 2.1
Name: pyjdbc
Version: 0.2.2
Summary: Use JDBC drivers to provide DB API 2.0 python database interface
Home-page: https://github.com/OpenBigDataPlatform/pyjdbc
Author: OpenBigDataPlatform
License: Apache-2.0
Keywords: dbapi jdbc
Platform: UNKNOWN
Classifier: Development Status :: 4 - Beta
Classifier: Intended Audience :: Developers
Classifier: Programming Language :: Java
Classifier: Programming Language :: Python :: 3
Classifier: Topic :: Database
Classifier: Topic :: Software Development :: Libraries :: Java Libraries
Classifier: Topic :: Software Development :: Libraries :: Python Modules
Requires-Dist: JPype1 (>=1.0.1)
Requires-Dist: sqlparams (>=3.0.0)
